README.md
README.txt
setup.cfg
setup.py
palpg/__init__.py
palpg.egg-info/PKG-INFO
palpg.egg-info/SOURCES.txt
palpg.egg-info/dependency_links.txt
palpg.egg-info/requires.txt
palpg.egg-info/top_level.txt