Metadata-Version: 1.2
Name: palpg
Version: 2.1
Summary: Postgres Wrapper Class using psycopg2
Home-page: https://github.com/ipal0/palpg
Author: Pal
Author-email: ipal0can@gmail.com
License: GPL
Platform: UNKNOWN
Requires-Python: >=3
